llama_index/packs/mixture_of_agents/__init__.py
llama_index/packs/mixture_of_agents/base.py
llama_index_packs_mixture_of_agents-0.4.1.dist-info/METADATA
llama_index_packs_mixture_of_agents-0.4.1.dist-info/WHEEL
llama_index_packs_mixture_of_agents-0.4.1.dist-info/licenses/LICENSE
llama_index_packs_mixture_of_agents-0.4.1.dist-info/RECORD
