Metadata-Version: 2.4
Name: llama-index-packs-mixture-of-agents
Version: 0.4.1
Summary: llama-index packs mixture_of_agents paper implementation
Author-email: Ravi Theja <ravi03071991@gmail.com>
Maintainer: ravi03071991
License-Expression: MIT
License-File: LICENSE
Keywords: agents,llms,query,togetherai
Requires-Python: <4.0,>=3.9
Requires-Dist: llama-index-core<0.15,>=0.13.0
